Workbook

Sheet Assumptions
A1: California Tribal Deployment — Cost Model
A2: Team of 3 · 6 Months · Generic Template
A4: TEAM — Monthly Rates
A5: Ahab (Architecture / Tech Lead) | B5: 8000 | C5: Core team
A6: Tarcila (Ops / Community Bridge) | B6: 8000 | C6: Core team — contract
A7: Developer/Engineer (Contract) | B7: 10000 | C7: Adjust to market/skill level
A9: TEAM — ALLOCATION (months active out of 6)
A10: Ahab — months active | B10: 6 | C10: Full duration
A11: Tarcila — months active | B11: 5 | C11: Phases 1,3,5,6 + overlap
A12: Developer — months active | B12: 4 | C12: Phases 2,4 + testing
A13: OVERHEAD — Monthly
A14: Legal / Entity | B14: 200 | C14: LLC + registered agent amortized
A15: Health Insurance | B15: 500 | C15: Sole proprietor marketplace
A16: Software / Tools | B16: 300 | C16: Claude, domains, dev tools
A17: Self-Employment Tax Rate | B17: 0.3 | C17: ~15.3% SE + ~15% effective income
A18: Contingency Rate | B18: 0.1 | C18: Buffer for unknowns
A19: TRAVEL — California (no international)
A20: Round-Trip Mileage/Gas per Visit | B20: 200 | C20: LA to tribal land — adjust for distance
A21: Per Diem (lodging + food) | B21: 150 | C21: Per person per day on-site
A22: Days per Visit | B22: 5 | C22: Mon-Fri on-site
A23: Number of Visits | B23: 6 | C23: Roughly monthly
A24: People Traveling | B24: 2 | C24: Ahab + Tarcila usually
A25: HARDWARE — Passthrough
A26: Devices (tablets/laptops) | B26: 2000 | C26: They likely have some already
A27: Networking (router/mesh) | B27: 500
A28: Backup/Storage Hardware | B28: 300 | C28: External drives, UPS
A29: Misc | B29: 500 | C29: Cases, cables, adapters
A30: CONSULTING — Outside Specialists
A31: Tribal Data Sovereignty Legal Review | B31: 3000 | C31: One-time — NAGPRA/OCAP compliance
A32: Language/Cultural Consultant (per session) | B32: 2000 | C32: If localization needed
A33: Number of Cultural Consult Sessions | B33: 3 | C33: Phases 1 and 3

Sheet 6-Month Model
A1: Factor 1: What It Costs You
A2: California Tribal · 6 Months · Team of 3
A4: TEAM COMPENSATION
A5: Ahab (6 months) | B5: =Assumptions!B5*Assumptions!B10 -> 48000 | C5: Full duration
A6: Tarcila (5 months) | B6: =Assumptions!B6*Assumptions!B11 -> 40000 | C6: Phases 1,3,5,6
A7: Developer/Engineer (4 months) | B7: =Assumptions!B7*Assumptions!B12 -> 40000 | C7: Phases 2,4 + testing
A8: Team Subtotal | B8: =SUM(B5:B7) -> 128000
A10: OVERHEAD (6 months)
A11: Legal + Health + Tools | B11: =(Assumptions!B14+Assumptions!B15+Assumptions!B16)*6 -> 6000
A13: TRAVEL
A14: Mileage/Gas (all visits) | B14: =Assumptions!B20*Assumptions!B23 -> 1200
A15: Per Diem (all visits) | B15: =Assumptions!B21*Assumptions!B22*Assumptions!B23*Assumptions!B24 -> 9000 | C15: rate × days × visits × people
A16: Travel Subtotal | B16: =SUM(B14:B15) -> 10200
A18: HARDWARE (passthrough)
A19: Hardware Total | B19: =Assumptions!B26+Assumptions!B27+Assumptions!B28+Assumptions!B29 -> 3300 | C19: Billed at cost
A21: OUTSIDE CONSULTANTS
A22: Legal Review (tribal data sovereignty) | B22: =Assumptions!B31 -> 3000
A23: Cultural/Language Consultant | B23: =Assumptions!B32*Assumptions!B33 -> 6000
A24: Consulting Subtotal | B24: =B22+B23 -> 9000
A26: TOTALS
A27: Project Subtotal (pre-tax/buffer) | B27: =B8+B11+B16+B19+B24 -> 156500
A28: Self-Employment Tax (Ahab comp only) | B28: =B5*Assumptions!B17 -> 14400 | C28: Tax on your earnings, not contractors
A29: Contingency Buffer | B29: =B27*Assumptions!B18 -> 15650
A31: TOTAL COST (What It Costs You) | B31: =B27+B28+B29 -> 186550
A33: Factor 2: What You Charge
A35: Margin Target | B35: 0.2 | C35: Adjust based on funder
A37: CHARGE TO CLIENT / GRANT | B37: =B31*(1+B35) -> 223860
A38: Gross Margin $ | B38: =B37-B31 -> 37310
A40: Grant Budget Breakdown
A41: Personnel — Core Team (Ahab + Tarcila) | B41: =B5+B6 -> 88000 | C41: =B41/B31 -> 0.4717234
A42: Personnel — Contracted Developer | B42: =B7 -> 40000 | C42: =B42/B31 -> 0.21441973
A43: Overhead & Administration | B43: =B11 -> 6000 | C43: =B43/B31 -> 0.032162959
A44: Travel & Per Diem | B44: =B16 -> 10200 | C44: =B44/B31 -> 0.05467703
A45: Equipment & Hardware | B45: =B19 -> 3300 | C45: =B45/B31 -> 0.017689627
A46: Consultants & Specialists | B46: =B24 -> 9000 | C46: =B46/B31 -> 0.048244438
A47: Tax & Contingency | B47: =B28+B29 -> 30050 | C47: =B47/B31 -> 0.16108282
A48: Total (pre-margin) | B48: =B31 -> 186550 | C48: 1

Sheet Phase Timeline
A1: Phase Timeline — 6 Month Deployment
A3: Phase | B3: Duration | C3: Ahab | D3: Tarcila | E3: Developer
A4: 1. Assessment & Governance Design | B4: 3 weeks | C4: Part-time | D4: Full-time | E4: —
A5: 2. Infrastructure & Hardware Setup | B5: 2 weeks | C5: Full-time | D5: — | E5: Full-time
A6: 3. Knowledge Seeding | B6: 6 weeks | C6: Part-time | D6: Full-time | E6: Part-time
A7: 4. Software Config & Testing | B7: 4 weeks | C7: Full-time | D7: — | E7: Full-time
A8: 5. Training & Capacity Building | B8: 4 weeks | C8: Part-time | D8: Full-time | E8: Part-time
A9: 6. Handoff & Sustainability | B9: 2 weeks | C9: Full-time | D9: Full-time | E9: —
A10: Buffer / Iteration | B10: 3 weeks | C10: As needed | D10: As needed | E10: As needed
A12: Total: ~24 weeks (6 months)

Sheet CA Tribal Notes
A1: California Tribal Deployment — Key Considerations
A4: WHAT CHANGES VS. INTERNATIONAL
A5: No solar needed — grid power available | B5: Saves $2,500+
A6: No international flights — driving distance | B6: Saves $8K+ per trip
A7: Better device availability | B7: May reduce hardware budget
A8: English as working language (usually) | B8: Less localization overhead
A9: LEGAL LANDSCAPE
A10: Tribal sovereignty has federal legal standing | B10: Different from international frameworks
A11: NAGPRA compliance if cultural objects/remains data | B11: Legal review covers this
A12: OCAP® principles align with Luna sovereignty model | B12: Natural fit for the pitch
A13: Tribal IRB may be required for knowledge seeding | B13: Build council relationship early
A14: CA AB 52 and tribal consultation requirements | B14: Legal review covers this
A15: TRUST & RELATIONSHIP
A16: History of extractive research programs | B16: Trust is earned, not assumed
A17: Tarcila leads community relationship | B17: Tech follows trust, not the other way around
A18: Start with Phase 1 as standalone engagement | B18: Let them evaluate before committing to full deployment
A19: GRANT LANDSCAPE
A20: Bureau of Indian Affairs (BIA) | B20: Tribal priority allocations
A21: IMLS (Institute of Museum & Library Services) | B21: Native American/Hawaiian Library Services grants
A22: NEA / NEH | B22: Cultural preservation and documentation
A23: First Nations Development Institute | B23: Capacity building grants
A24: California tribal-specific state programs | B24: Research current offerings
