Workbook

Sheet Summary
A1: LUNA / ECLISSI DEVELOPMENT COST BREAKDOWN
A2: Project Tapestry — Sovereign AI Infrastructure
A4: LABOR RATE TIERS
A5: Tier | B5: Hourly Rate | C5: Description | D5: Use Case
A6: Nonprofit/Grant | B6: 75 | C6: Discounted rate for mission-aligned work | D6: Grant budgets, nonprofit partnerships
A7: Market Rate | B7: 150 | C7: Standard senior architect/full-stack rate | D7: Commercial contracts, "true cost" valuation
A8: Premium/Consulting | B8: 200 | C8: Specialist rate for AI/sovereignty expertise | D8: High-stakes consulting, expert testimony
A10: DEVELOPMENT PHASES — TOTAL COST BY TIER
A11: Phase | B11: Timeline | C11: Hours | D11: Nonprofit ($75/hr) | E11: Market ($150/hr) | F11: Premium ($200/hr)
A12: Phase 1: ROSA Demo Prototype | B12: 2 months (Jan-Mar 2026) | C12: 320 | D12: =C12*75 -> 24000 | E12: =C12*150 -> 48000 | F12: =C12*200 -> 64000
A13: Phase 2: MVP / Year 1 | B13: 10 months (Mar 2026 - Jan 2027) | C13: 1200 | D13: =C13*75 -> 90000 | E13: =C13*150 -> 180000 | F13: =C13*200 -> 240000
A14: Phase 3: Year 2 Scaling | B14: 12 months (2027) | C14: 1600 | D14: =C14*75 -> 120000 | E14: =C14*150 -> 240000 | F14: =C14*200 -> 320000
A15: TOTAL (All Phases) | C15: =SUM(C12:C14) -> 3120 | D15: =SUM(D12:D14) -> 234000 | E15: =SUM(E12:E14) -> 468000 | F15: =SUM(F12:F14) -> 624000

Sheet Phase 1 - ROSA Demo
A1: PHASE 1: ROSA CONFERENCE DEMO PROTOTYPE
A2: Timeline: January - March 2026 (8 weeks)
A4: Task Category | B4: Description | C4: Hours | D4: Nonprofit | E4: Market | F4: Premium
A5: Luna Core Engine | B5: SQLite memory system, context management, basic inference pipeline | C5: 80 | D5: =C5*75 -> 6000 | E5: =C5*150 -> 12000 | F5: =C5*200 -> 16000
A6: Eclissi Database Schema | B6: Knowledge graph structure, clan-based access control design | C6: 40 | D6: =C6*75 -> 3000 | E6: =C6*150 -> 6000 | F6: =C6*200 -> 8000
A7: Luna ↔ Eclissi Bridge | B7: API layer connecting companion to cultural database | C7: 32 | D7: =C7*75 -> 2400 | E7: =C7*150 -> 4800 | F7: =C7*200 -> 6400
A8: Luganda LLM Integration | B8: Ganda Gemma 1B integration, Ollama setup, quantization testing | C8: 40 | D8: =C8*75 -> 3000 | E8: =C8*150 -> 6000 | F8: =C8*200 -> 8000
A9: Demo UI/UX | B9: Minimal viable interface for conference presentation | C9: 48 | D9: =C9*75 -> 3600 | E9: =C9*150 -> 7200 | F9: =C9*200 -> 9600
A10: Hardware Integration | B10: Raspberry Pi / edge device setup, offline deployment packaging | C10: 32 | D10: =C10*75 -> 2400 | E10: =C10*150 -> 4800 | F10: =C10*200 -> 6400
A11: Testing & QA | B11: Integration testing, edge case handling, demo rehearsal | C11: 24 | D11: =C11*75 -> 1800 | E11: =C11*150 -> 3600 | F11: =C11*200 -> 4800
A12: Documentation | B12: Technical docs, demo script, presentation materials | C12: 24 | D12: =C12*75 -> 1800 | E12: =C12*150 -> 3600 | F12: =C12*200 -> 4800
A13: PHASE 1 TOTAL | C13: =SUM(C5:C12) -> 320 | D13: =SUM(D5:D12) -> 24000 | E13: =SUM(E5:E12) -> 48000 | F13: =SUM(F5:F12) -> 64000
A15: NON-LABOR COSTS (Phase 1)
A16: Item | B16: Description | C16: Cost
A17: Edge Compute Device | B17: Raspberry Pi 5 (8GB) + case + power supply | C17: 150
A18: Development Hardware | B18: SSD, cables, peripherals for testing | C18: 200
A19: Cloud Compute (Dev) | B19: GPU instances for model testing (2 months) | C19: 300
A20: Software/Services | B20: API costs, development tools, licenses | C20: 150
A21: Conference Costs | B21: Demo equipment, travel support if in-person component | C21: 500
A22: Non-Labor Subtotal | C22: =SUM(C17:C21) -> 1300

Sheet Phase 2 - MVP Year 1
A1: PHASE 2: MVP / YEAR 1 DEVELOPMENT
A2: Timeline: March 2026 - January 2027 (10 months)
A4: Task Category | B4: Description | C4: Hours | D4: Nonprofit | E4: Market | F4: Premium
A5: Luna Memory System V2 | B5: Advanced memory architecture, relationship modeling, context windows | C5: 160 | D5: =C5*75 -> 12000 | E5: =C5*150 -> 24000 | F5: =C5*200 -> 32000
A6: Eclissi Full Implementation | B6: Complete knowledge graph, multi-tribe support, version control | C6: 200 | D6: =C6*75 -> 15000 | E6: =C6*150 -> 30000 | F6: =C6*200 -> 40000
A7: Access Control System | B7: Clan-based permissions, elder override, TK Labels integration | C7: 120 | D7: =C7*75 -> 9000 | E7: =C7*150 -> 18000 | F7: =C7*200 -> 24000
A8: Multi-language Support | B8: Beyond Luganda: framework for additional languages | C8: 80 | D8: =C8*75 -> 6000 | E8: =C8*150 -> 12000 | F8: =C8*200 -> 16000
A9: Offline Sync Engine | B9: Peer-to-peer sync, conflict resolution, data sovereignty | C9: 120 | D9: =C9*75 -> 9000 | E9: =C9*150 -> 18000 | F9: =C9*200 -> 24000
A10: Mobile Application | B10: Cross-platform (React Native or Flutter), tablet-optimized | C10: 160 | D10: =C10*75 -> 12000 | E10: =C10*150 -> 24000 | F10: =C10*200 -> 32000
A11: Voice Interface | B11: Speech-to-text, text-to-speech for oral tradition support | C11: 80 | D11: =C11*75 -> 6000 | E11: =C11*150 -> 12000 | F11: =C11*200 -> 16000
A12: Cultural Content Tools | B12: Elder recording interface, story capture, media handling | C12: 80 | D12: =C12*75 -> 6000 | E12: =C12*150 -> 12000 | F12: =C12*200 -> 16000
A13: Admin Dashboard | B13: Hub management, usage analytics, content moderation | C13: 60 | D13: =C13*75 -> 4500 | E13: =C13*150 -> 9000 | F13: =C13*200 -> 12000
A14: Security Hardening | B14: Encryption, secure enclaves, penetration testing | C14: 60 | D14: =C14*75 -> 4500 | E14: =C14*150 -> 9000 | F14: =C14*200 -> 12000
A15: Integration Testing | B15: Full system testing, Kinoni pilot preparation | C15: 40 | D15: =C15*75 -> 3000 | E15: =C15*150 -> 6000 | F15: =C15*200 -> 8000
A16: Documentation & Training | B16: User guides, facilitator training materials | C16: 40 | D16: =C16*75 -> 3000 | E16: =C16*150 -> 6000 | F16: =C16*200 -> 8000
A17: PHASE 2 TOTAL | C17: =SUM(C5:C16) -> 1200 | D17: =SUM(D5:D16) -> 90000 | E17: =SUM(E5:E16) -> 180000 | F17: =SUM(F5:F16) -> 240000

Sheet Infrastructure Tiers
A1: KINONI ICT HUB — INFRASTRUCTURE COST PROJECTIONS
A2: Tiered deployment options for different funding scenarios
A4: TIER DEFINITIONS
A5: Tier | B5: Description | C5: Capacity | D5: Use Case
A6: Minimal | B6: Proof of concept, single location | C6: 5-10 concurrent users | D6: ROSA demo, pilot testing
A7: Standard | B7: Functional community hub | C7: 20-30 concurrent users | D7: Year 1 Kinoni deployment
A8: Full | B8: Complete implementation | C8: 50+ concurrent users | D8: Scaled regional hub
A10: YEAR 1 INFRASTRUCTURE COSTS
A11: Category | B11: Item | C11: Minimal | D11: Standard | E11: Full
A12: Power | B12: Solar panels + batteries | C12: 3000 | D12: 8000 | E12: 15000
A13: Power | B13: Installation & wiring | C13: 500 | D13: 1500 | E13: 3000
A14: Power | B14: Backup generator | C14: 0 | D14: 800 | E14: 1500
A15: Connectivity | B15: Starlink kit | C15: 600 | D15: 600 | E15: 600
A16: Connectivity | B16: Starlink service (12 mo) | C16: 1440 | D16: 1440 | E16: 1440
A17: Connectivity | B17: Local mesh network | C17: 0 | D17: 500 | E17: 1500
A18: Devices | B18: Tablets (Android) | C18: 1000 | D18: 4000 | E18: 10000
A19: Devices | B19: Raspberry Pi units | C19: 300 | D19: 900 | E19: 2000
A20: Devices | B20: Charging station | C20: 200 | D20: 500 | E20: 1000
A21: Devices | B21: Protective cases/accessories | C21: 200 | D21: 600 | E21: 1500
A22: Facility | B22: Furniture (tables, chairs) | C22: 300 | D22: 800 | E22: 2000
A23: Facility | B23: Security (locks, safe) | C23: 100 | D23: 300 | E23: 500
A24: Facility | B24: Signage & branding | C24: 100 | D24: 250 | E24: 500
A25: Operations | B25: Maintenance reserve (10%) | C25: =SUM(C12:C24)*0.1 -> 774 | D25: =SUM(D12:D24)*0.1 -> 2019 | E25: =SUM(E12:E24)*0.1 -> 4054
A26: YEAR 1 TOTAL | C26: =SUM(C12:C25) -> 8514 | D26: =SUM(D12:D25) -> 22209 | E26: =SUM(E12:E25) -> 44594
A28: ANNUAL RECURRING COSTS (Year 2+)
A29: Category | B29: Item | C29: Minimal | D29: Standard | E29: Full
A30: Connectivity | B30: Starlink service (12 mo) | C30: 1440 | D30: 1440 | E30: 1440
A31: Operations | B31: Device replacement (15%) | C31: 150 | D31: 550 | E31: 1350
A32: Operations | B32: Maintenance & repairs | C32: 300 | D32: 800 | E32: 1500
A33: Operations | B33: Consumables (power, etc.) | C33: 200 | D33: 400 | E33: 800
A34: ANNUAL RECURRING | C34: =SUM(C30:C33) -> 2090 | D34: =SUM(D30:D33) -> 3190 | E34: =SUM(E30:E33) -> 5090

Sheet Robotics (Separate)
A1: LUNA ROBOTICS — PHYSICAL CHASSIS (SEPARATE BUDGET)
A2: Note: This is tracked separately from software development
A4: Component | B4: Description | C4: Est. Cost | D4: Status
A5: Chassis/Shell | B5: 3D printed or fabricated enclosure | C5: 500 | D5: Design phase
A6: Display Module | B6: Galaxy face display (OLED/LCD) | C6: 150 | D6: Sourcing
A7: Ball-joint Base | B7: 360° rotation mechanism | C7: 200 | D7: Design phase
A8: Retractable Neck | B8: Expressive movement system | C8: 300 | D8: Concept
A9: Compute Module | B9: Raspberry Pi 5 or Jetson Nano | C9: 150 | D9: Specified
A10: Audio System | B10: Speakers + microphone array | C10: 100 | D10: Sourcing
A11: Power System | B11: Battery + charging circuit | C11: 150 | D11: Design phase
A12: Sensors | B12: Proximity, touch, ambient light | C12: 100 | D12: TBD
A13: Assembly/Fabrication | B13: Labor for physical build | C13: 1000 | D13: TBD
A14: Dust Protection | B14: Desert-rated sealing | C14: 200 | D14: TBD
A15: ROBOTICS TOTAL | C15: =SUM(C5:C14) -> 2850

Sheet Total Project Cost
A1: TOTAL PROJECT COST — ALL COMPONENTS
A3: YEAR 1 TOTAL BY LABOR TIER (Software + Infrastructure)
A4: Component | B4: Nonprofit ($75/hr) | C4: Market ($150/hr) | D4: Premium ($200/hr)
A5: Phase 1 Labor (ROSA Demo) | B5: ='Phase 1 - ROSA Demo'!D13 -> 24000 | C5: ='Phase 1 - ROSA Demo'!E13 -> 48000 | D5: ='Phase 1 - ROSA Demo'!F13 -> 64000
A6: Phase 1 Non-Labor | B6: ='Phase 1 - ROSA Demo'!C21 -> 500 | C6: ='Phase 1 - ROSA Demo'!C21 -> 500 | D6: ='Phase 1 - ROSA Demo'!C21 -> 500
A7: Phase 2 Labor (MVP) | B7: ='Phase 2 - MVP Year 1'!D17 -> 90000 | C7: ='Phase 2 - MVP Year 1'!E17 -> 180000 | D7: ='Phase 2 - MVP Year 1'!F17 -> 240000
A8: Infrastructure (Standard Tier) | B8: ='Infrastructure Tiers'!D26 -> 22209 | C8: ='Infrastructure Tiers'!D26 -> 22209 | D8: ='Infrastructure Tiers'!D26 -> 22209
A9: YEAR 1 TOTAL | B9: =SUM(B5:B8) -> 136709 | C9: =SUM(C5:C8) -> 250709 | D9: =SUM(D5:D8) -> 326709
A12: QUICK REFERENCE — ROSA DEMO ONLY
A13: Phase 1 Labor + Non-Labor: | B13: =B5+B6 -> 24500 | C13: =C5+C6 -> 48500 | D13: =D5+D6 -> 64500
